CCParse/Enums.py
CCParse/__init__.py
CCParse/ccbase.py
CCParse/ccdecode.py
CCParse/models/__init__.py
CCParse/models/ccmobile.py
CCParse/models/ccmobilebuildings.py
CCParse/models/ccpc.py
CookieClickerSaveParser-1.0.0.dist-info/LICENSE
CookieClickerSaveParser-1.0.0.dist-info/METADATA
CookieClickerSaveParser-1.0.0.dist-info/WHEEL
CookieClickerSaveParser-1.0.0.dist-info/top_level.txt
CookieClickerSaveParser-1.0.0.dist-info/RECORD
